gpu_benchmark_linux/__init__.py
gpu_benchmark_linux/__main__.py
gpu_benchmark_linux/benchmark.py
gpu_benchmark_linux/chart_generator.py
gpu_benchmark_linux/csv_logger.py
gpu_benchmark_linux/csv_viewer.py
gpu_benchmark_linux/cuda_ops.py
gpu_benchmark_linux/demo_test.py
gpu_benchmark_linux/detailed_logger.py
gpu_benchmark_linux/enhanced_html_reporter.py
gpu_benchmark_linux/enhanced_reporter.py
gpu_benchmark_linux/exceptions.py
gpu_benchmark_linux/gpu_profiles.py
gpu_benchmark_linux/gpu_specs_update.py
gpu_benchmark_linux/html_reporter.py
gpu_benchmark_linux/memory_optimizer.py
gpu_benchmark_linux/monitor.py
gpu_benchmark_linux/multi_precision_performance.py
gpu_benchmark_linux/optimized_stress_test.py
gpu_benchmark_linux/performance_summary.py
gpu_benchmark_linux/reporter.py
gpu_benchmark_linux/safe_model_inference_test.py
gpu_benchmark_linux/stress_test.py
gpu_benchmark_linux/utils.py
gpu_benchmark_linux/tests/__init__.py
gpu_benchmark_linux/tests/cuda_tests.py
gpu_benchmark_linux/tests/model_tests.py
gpu_benchmark_linux-0.4.4.dist-info/licenses/LICENSE
gpu_benchmark_linux-0.4.4.dist-info/METADATA
gpu_benchmark_linux-0.4.4.dist-info/WHEEL
gpu_benchmark_linux-0.4.4.dist-info/entry_points.txt
gpu_benchmark_linux-0.4.4.dist-info/top_level.txt
gpu_benchmark_linux-0.4.4.dist-info/RECORD
