Metadata-Version: 2.4
Name: gpu-benchmark-linux
Version: 0.4.4
Summary: GPU基准测试工具 - 用于评估NVIDIA GPU性能的综合工具包
Author-email: GPU Benchmark Team <your.email@example.com>
License: MIT
Project-URL: Homepage, https://github.com/yourusername/gpu-benchmark-linux
Project-URL: Bug Tracker, https://github.com/yourusername/gpu-benchmark-linux/issues
Project-URL: Documentation, https://github.com/yourusername/gpu-benchmark-linux#readme
Keywords: gpu,benchmark,cuda,nvidia,testing,performance
Classifier: Programming Language :: Python :: 3
Classifier: License :: OSI Approved :: MIT License
Classifier: Operating System :: OS Independent
Classifier: Development Status :: 4 - Beta
Classifier: Intended Audience :: Developers
Classifier: Intended Audience :: Science/Research
Classifier: Topic :: Scientific/Engineering
Classifier: Topic :: System :: Benchmark
Requires-Python: >=3.7
License-File: LICENSE
Requires-Dist: torch
Requires-Dist: transformers
Requires-Dist: diffusers
Requires-Dist: accelerate
Requires-Dist: sentencepiece
Requires-Dist: numpy
Requires-Dist: tqdm
Requires-Dist: colorama
Requires-Dist: gitpython
Requires-Dist: cupy-cuda12x>=12.0.0
Requires-Dist: pycuda>=2023.1
Requires-Dist: nvidia-ml-py3>=7.352.0
Requires-Dist: psutil>=5.9.0
Dynamic: license-file
